odoo/addons/product_category_usage_group/README.rst
odoo/addons/product_category_usage_group/__init__.py
odoo/addons/product_category_usage_group/__manifest__.py
odoo/addons/product_category_usage_group/demo/product_category.xml
odoo/addons/product_category_usage_group/i18n/fr.po
odoo/addons/product_category_usage_group/i18n/product_category_usage_group.pot
odoo/addons/product_category_usage_group/models/__init__.py
odoo/addons/product_category_usage_group/models/product_category.py
odoo/addons/product_category_usage_group/models/product_template.py
odoo/addons/product_category_usage_group/readme/CONFIGURE.rst
odoo/addons/product_category_usage_group/readme/CONTRIBUTORS.rst
odoo/addons/product_category_usage_group/readme/DESCRIPTION.rst
odoo/addons/product_category_usage_group/static/description/icon.png
odoo/addons/product_category_usage_group/static/description/index.html
odoo/addons/product_category_usage_group/static/description/product_category_form.png
odoo/addons/product_category_usage_group/static/description/product_template_warning.png
odoo/addons/product_category_usage_group/tests/__init__.py
odoo/addons/product_category_usage_group/tests/test_module.py
odoo/addons/product_category_usage_group/views/view_product_category.xml
odoo_addon_product_category_usage_group-16.0.1.0.0.2.dist-info/METADATA
odoo_addon_product_category_usage_group-16.0.1.0.0.2.dist-info/WHEEL
odoo_addon_product_category_usage_group-16.0.1.0.0.2.dist-info/top_level.txt
odoo_addon_product_category_usage_group-16.0.1.0.0.2.dist-info/RECORD
